{
  "users": {
    "testaccount": {
      "passwordHash": "$2a$10$uHWY5dY.40FonBVdbju.Q.sYI/nzzkQcpM0sJGd9G9Xa8gdWfkqpu",
      "data": {
        "firstname": "Test",
        "lastname": "Account",
        "favbar": "Bobs"
      }
    },
    "test1": {
      "passwordHash": "$2a$10$ZgmhwanovVscg2FsAG.maeQ/.t0B3BlXGjjJSEfvLntWlAz8fOFpW",
      "data": {
        "firstname": "Test",
        "lastname": "Account",
        "favbar": "Bobs"
      }
    },
    "willbenson97": {
      "passwordHash": "$2a$10$dCRhROaDiN9YDVENHVBU1u3vSXOz0Mo7pDz27ciUjoEJ3ik9Sa7HS",
      "data": {
        "firstname": "Will",
        "lastname": "Benson",
        "favbar": "Bobs"
      }
    },
    "testaccount1": {
      "passwordHash": "$2a$10$BYF2FqR.KzYetgHkFfCItuPPvNLVIZ9vsx.N4lvMv2lNKMzikLuqm",
      "data": {
        "firstname": "test",
        "lastname": "account",
        "favbar": "Bobs"
      }
    },
    "testaccount2": {
      "passwordHash": "$2a$10$AqTfFOK0.VWRdIVUCRqV8.KlKhZ2KAlO9SdQ1bqUK8jOy6pvZQm2S",
      "data": {
        "firstname": "Test",
        "lastname": "Account",
        "favbar": "La"
      }
    },
    "testaccount3": {
      "passwordHash": "$2a$10$eQH/iQ6BDcz38LeGpGXBAOYhgxmNL31GqszPRMcLbKZT4r.wclfHW",
      "data": {
        "firstname": "Test",
        "lastname": "Account",
        "favbar": "Pantana"
      }
    },
    "testaccount5": {
      "passwordHash": "$2a$10$rlngO4YGNPodEikwK5OR6.Tq449VNrLx6qLGywld2i16O3jzRyzJS",
      "data": {
        "firstname": "Test",
        "lastname": "Account"
      }
    },
    "testaccount6": {
      "passwordHash": "$2a$10$j6ObPpDkkyYX8pQUayKYheWolK9aoPr6ueh1y3u/a1wkMG75./CH.",
      "data": {
        "firstname": "Test",
        "lastname": "Account"
      }
    },
    "testaccount7": {
      "passwordHash": "$2a$10$0vXoYGU6pMEU/75ev/hK9epjNEyMAKCh5tpW/0MchSB9hscRLd9X6",
      "data": {
        "firstname": "Test",
        "lastname": "Account"
      }
    },
    "testaccount8": {
      "passwordHash": "$2a$10$XNzHThjz7yHIpEP.7pNehuFTJhV8z3hodrC9dIL0QR0W.pWCfJlWS",
      "data": {
        "firstname": "Test",
        "lastname": "Account"
      }
    },
    "testaccount9": {
      "passwordHash": "$2a$10$4Ewqo6Kb/Kh6G2nxuE1m..JBBfcS.L.82Dy2nYxsCoCsdPYh/Nd8m",
      "data": {
        "firstname": "Test",
        "lastname": "Account",
        "favbar": "Pantana"
      }
    },
    "testaccount10": {
      "passwordHash": "$2a$10$rtPCx.Z8HsomNcKD9gXVPuiktg25BrGYMBrdm6W/dnf4sTf8f5eJm",
      "data": {
        "firstname": "Test",
        "lastname": "Account",
        "favbar": "Pantana"
      }
    },
    "testaccount11": {
      "passwordHash": "$2a$10$nFwgB.TebkC1XncKHGSVZeER4mMtBrOJQgosJvX3UJpdWoOCuaC2y",
      "data": {
        "firstname": "Test",
        "lastname": "Account",
        "favbar": "Pantana"
      }
    },
    "testaccount12": {
      "passwordHash": "$2a$10$Z.MI.rA2REwnuOaJUIvrJulNpbc3tJv2WiJJmlfppXenVkPMOeDRS",
      "data": {
        "firstname": "Test",
        "lastname": "Account",
        "favbar": "Pantana"
      }
    },
    "testaccount13": {
      "passwordHash": "$2a$10$r6/HT.RvMQWgVU0GY3fPWO123kwbzQfEKlK5rt7R2uA5V8qIh/6jq",
      "data": {
        "firstname": "Test",
        "lastname": "Account",
        "favbar": "Pantana"
      }
    },
    "testedaccount1": {
      "passwordHash": "$2a$10$xzFJFH/VTir95oygyQfLGOiaztoj5jAXYv66EURdOE15SdtepntBe",
      "data": {
        "firstname": "Tested",
        "lastname": "Account",
        "favbar": "Pantana"
      }
    },
    "testaccount20": {
      "passwordHash": "$2a$10$A..7MA/8lB4hXTFHeNPGgekvwDv1ELrG8ojCrlGlKCk2hCiUUexKq",
      "data": {
        "firstname": "Test",
        "lastname": "Account",
        "favbar": "Pantana"
      }
    },
    "testaccount21": {
      "passwordHash": "$2a$10$iM.FewXoBRCddJ2Jg7KGN.hSVMyY5tfoBPZ49U4yuFB4j8P3jmNPO",
      "data": {
        "firstname": "Test",
        "lastname": "Account",
        "favbar": "Pantana"
      }
    },
    "testaccount23": {
      "passwordHash": "$2a$10$EeWYuBHSEdmRa4a7vzC39Oi/Pu0wVAScMMs8lRUhwPcCRr90RWX.a",
      "data": {
        "firstname": "Test",
        "lastname": "Account",
        "favbar": "Pantana"
      }
    },
    "testaccount30": {
      "passwordHash": "$2a$10$9NxEHZpL4Mm9shQrRUGRoOgcPI4avWFnRbIzQNcFCSpTSVbKWXMPa",
      "data": {
        "firstname": "test",
        "lastname": "account",
        "favbar": "Goodfellows"
      }
    },
    "willbenson": {
      "passwordHash": "$2a$10$73AiiH0EBwxKSXbuiF85.Ob0hm.SNKXsIVQWiS2/WRRPEUpDz8GMm",
      "data": {
        "firstname": "Will",
        "lastname": "Benson",
        "favbar": "He's Not Here"
      }
    },
    "willbenson497": {
      "passwordHash": "$2a$10$CXzLLVBftHEHN7Fz/Y84F.E38tK2zYj8xISKS85Antf4TwAYITstq",
      "data": {
        "firstname": "Will",
        "lastname": "Benson",
        "favbar": "Dead Mule Club"
      }
    },
    "rrd": {
      "passwordHash": "$2a$10$ADhQZNAR7kKSh00g10jtPeTWLXC3YmLLG29N1DRmCwbl8pm9hh8F2",
      "data": {
        "firstname": "Rhett",
        "lastname": "Dudley",
        "favbar": "Pantana Bob's"
      }
    },
    "ptrams": {
      "passwordHash": "$2a$10$5olbEXg4C.Qb/7Ls2o3eS.PlH9IscFDPMMmrXeVWqdyubO7lb.0.a",
      "data": {
        "firstname": "Phil",
        "lastname": "Smart",
        "favbar": "Might As Well Bar & Grill"
      }
    }
  }
}